mkdocs_glossary_plugin/__init__.py
mkdocs_glossary_plugin/plugin.py
mkdocs_glossary_plugin/converter/AlignCenterConverter.py
mkdocs_glossary_plugin/converter/AlignDefaultConverter.py
mkdocs_glossary_plugin/converter/AlignLeftConverter.py
mkdocs_glossary_plugin/converter/AlignRightConverter.py
mkdocs_glossary_plugin/converter/AlignmentConverter.py
mkdocs_glossary_plugin/converter/AttrConverter.py
mkdocs_glossary_plugin/converter/AuthorInTextConverter.py
mkdocs_glossary_plugin/converter/BaseConverter.py
mkdocs_glossary_plugin/converter/BlockConverter.py
mkdocs_glossary_plugin/converter/BlockQuoteConverter.py
mkdocs_glossary_plugin/converter/BoolConverter.py
mkdocs_glossary_plugin/converter/BuiltInTypeConverter.py
mkdocs_glossary_plugin/converter/BulletListConverter.py
mkdocs_glossary_plugin/converter/CaptionConverter.py
mkdocs_glossary_plugin/converter/CellConverter.py
mkdocs_glossary_plugin/converter/CitationConverter.py
mkdocs_glossary_plugin/converter/CitationModeConverter.py
mkdocs_glossary_plugin/converter/CiteConverter.py
mkdocs_glossary_plugin/converter/CodeBlockConverter.py
mkdocs_glossary_plugin/converter/CodeConverter.py
mkdocs_glossary_plugin/converter/ColSpanConverter.py
mkdocs_glossary_plugin/converter/ColSpecConverter.py
mkdocs_glossary_plugin/converter/ColWidthConverter.py
mkdocs_glossary_plugin/converter/ColWidthDefaultConverter.py
mkdocs_glossary_plugin/converter/ColWidth_Converter.py
mkdocs_glossary_plugin/converter/DecimalConverter.py
mkdocs_glossary_plugin/converter/DefaultDelimConverter.py
mkdocs_glossary_plugin/converter/DefaultStyleConverter.py
mkdocs_glossary_plugin/converter/DefinitionListConverter.py
mkdocs_glossary_plugin/converter/DisplayMathConverter.py
mkdocs_glossary_plugin/converter/DivConverter.py
mkdocs_glossary_plugin/converter/DoubleConverter.py
mkdocs_glossary_plugin/converter/DoubleQuoteConverter.py
mkdocs_glossary_plugin/converter/EmphConverter.py
mkdocs_glossary_plugin/converter/ExampleConverter.py
mkdocs_glossary_plugin-0.1.1.dist-info/LICENSE
mkdocs_glossary_plugin-0.1.1.dist-info/METADATA
mkdocs_glossary_plugin-0.1.1.dist-info/WHEEL
mkdocs_glossary_plugin-0.1.1.dist-info/entry_points.txt
mkdocs_glossary_plugin-0.1.1.dist-info/top_level.txt
mkdocs_glossary_plugin-0.1.1.dist-info/RECORD
