Metadata-Version: 2.1
Name: mkdocs-glossary-plugin
Version: 0.1.1
Summary: This plugin automatically turns specific words into links to specific pages.
Home-page: https://github.com/AngryMane/mkdocs-glossary-plugin
Author: AngryMane
Author-email: regulationdango@gmail.com
License: MIT
Keywords: mkdocs
Platform: UNKNOWN
Classifier: Development Status :: 4 - Beta
Classifier: Environment :: Plugins
Classifier: Topic :: Documentation
Classifier: Intended Audience :: Developers
Classifier: Intended Audience :: Information Technology
Classifier: License :: OSI Approved :: MIT License
Classifier: Programming Language :: Python
Classifier: Programming Language :: Python :: 3 :: Only
Requires-Python: >=3.7
License-File: LICENSE
Requires-Dist: mkdocs (>=1.0.3)
Requires-Dist: pandoc
